sacapi/__init__.py
sacapi/sacapi.py
sacapi-1.0.1.dist-info/LICENSE
sacapi-1.0.1.dist-info/METADATA
sacapi-1.0.1.dist-info/WHEEL
sacapi-1.0.1.dist-info/top_level.txt
sacapi-1.0.1.dist-info/RECORD
