Metadata-Version: 2.1
Name: sacapi
Version: 1.0.1
Summary: An example package for exporting data from SAP Analytics Cloud or importing data into it, or working with it in Python tools
Author-email: David Stocker <david.stocker@sap.com>
License: Apache License
Project-URL: Homepage, https://github.com/SAP-samples/analytics-cloud-export-api-wrapper
Project-URL: Bug Tracker, https://github.com/SAP-samples/analytics-cloud-export-api-wrapper/issues
Classifier: Programming Language :: Python :: 3
Classifier: License :: OSI Approved :: Apache Software License
Classifier: Operating System :: OS Independent
Requires-Python: >=3.10
License-File: LICENSE
Requires-Dist: oauthlib >=3.2.2
Requires-Dist: requests-oauthlib >=1.3.1
